whitespace_normalizer/__init__.py
whitespace_normalizer-2025.9.14911.dist-info/licenses/LICENSE
whitespace_normalizer-2025.9.14911.dist-info/METADATA
whitespace_normalizer-2025.9.14911.dist-info/WHEEL
whitespace_normalizer-2025.9.14911.dist-info/top_level.txt
whitespace_normalizer-2025.9.14911.dist-info/RECORD
