Metadata-Version: 2.4
Name: whitespace_normalizer
Version: 2025.9.14911
Summary: import re   def compress_whitespace(text: str) -> str:     """     Collapse runs of spaces/tabs to a single space on each line, trim traili…
Author-email: Eugene Evstafev <hi@eugene.plus>
License: MIT License
Project-URL: Repository, https://pypi.org/project/whitespace_normalizer/
Requires-Python: >=3.9
License-File: LICENSE
Dynamic: license-file
